aaa_mingshe.pth
mingshe/__init__.py
mingshe/__main__.py
mingshe/__version__.py
mingshe/_vendor/README.md
mingshe/_vendor/pegen/__init__.py
mingshe/_vendor/pegen/__main__.py
mingshe/_vendor/pegen/build.py
mingshe/_vendor/pegen/first_sets.py
mingshe/_vendor/pegen/grammar.py
mingshe/_vendor/pegen/grammar_parser.py
mingshe/_vendor/pegen/grammar_visualizer.py
mingshe/_vendor/pegen/metagrammar.gram
mingshe/_vendor/pegen/parser.py
mingshe/_vendor/pegen/parser_generator.py
mingshe/_vendor/pegen/python_generator.py
mingshe/_vendor/pegen/sccutils.py
mingshe/_vendor/pegen/templates/index.html
mingshe/_vendor/pegen/tokenizer.py
mingshe/_vendor/pegen/validator.py
mingshe/_vendor/pegen/web.py
mingshe/commands.py
mingshe/core.py
mingshe/importlib.py
mingshe/parser.py
mingshe/utils.py
mingshe-0.8.2.dist-info/entry_points.txt
mingshe-0.8.2.dist-info/WHEEL
mingshe-0.8.2.dist-info/METADATA
mingshe-0.8.2.dist-info/LICENSE
mingshe-0.8.2.dist-info/RECORD
