Metadata-Version: 2.1
Name: mingshe
Version: 0.8.2
Summary: A better Python superset language.
License: Apache-2.0
Author-email: abersheeran <me@abersheeran.com>
Requires-Python: >=3.9
Classifier: Programming Language :: Python :: 3
Project-URL: homepage, https://github.com/abersheeran/mingshe
Project-URL: repository, https://github.com/abersheeran/mingshe
